llm_perf_tools/__init__.py
llm_perf_tools/gpu.py
llm_perf_tools/inference.py
llm_perf_tools/types.py
llm_perf_tools/utils.py
llm_perf_tools/visualization.py
llm_perf_tools-0.2.0.dist-info/LICENSE
llm_perf_tools-0.2.0.dist-info/METADATA
llm_perf_tools-0.2.0.dist-info/WHEEL
llm_perf_tools-0.2.0.dist-info/RECORD
