Metadata-Version: 2.3
Name: llm-perf-tools
Version: 0.2.0
Summary: Tool for monitoring LLM inference metrics
Author: codepydog
Author-email: codepydog@gmail.com
Requires-Python: >=3.10,<3.14
Classifier: Programming Language :: Python :: 3
Classifier: Programming Language :: Python :: 3.10
Classifier: Programming Language :: Python :: 3.11
Classifier: Programming Language :: Python :: 3.12
Classifier: Programming Language :: Python :: 3.13
Requires-Dist: matplotlib (>=3.9.0,<4.0.0)
Requires-Dist: nvidia-ml-py (>=13.580.82,<14.0.0)
Requires-Dist: openai (>=1.107.0)
Requires-Dist: pydantic (>=2.11.7)
Requires-Dist: python-dotenv (>=1.1.1,<2.0.0)
Requires-Dist: rich (>=14.1.0,<15.0.0)
Requires-Dist: seaborn (>=0.13.0,<0.14.0)
